config/__init__.py
config/config38M.json
config/config640M.json
config/configMSA-600M.json
config/configMSA.json
evodiff/__init__.py
evodiff/collaters.py
evodiff/conditional_generation.py
evodiff/conditional_generation_msa.py
evodiff/constants.py
evodiff/data.py
evodiff/generate.py
evodiff/generate_msa.py
evodiff/losses.py
evodiff/metrics.py
evodiff/model.py
evodiff/plot.py
evodiff/pretrained.py
evodiff/utils.py
evodiff-1.1.2.dist-info/licenses/LICENSE
evodiff-1.1.2.dist-info/METADATA
evodiff-1.1.2.dist-info/WHEEL
evodiff-1.1.2.dist-info/top_level.txt
evodiff-1.1.2.dist-info/RECORD
