Metadata-Version: 2.4
Name: evodiff
Version: 1.1.2
Summary: Python package for generation of protein sequences and evolutionary alignments via discrete diffusion models
Home-page: https://github.com/microsoft/evodiff
Classifier: Programming Language :: Python :: 3
Classifier: License :: OSI Approved :: MIT License
Classifier: Operating System :: OS Independent
Requires-Python: >=3.9.0
License-File: LICENSE
Requires-Dist: biopython
Requires-Dist: blosum
Requires-Dist: fair-esm
Requires-Dist: lmdb
Requires-Dist: matplotlib
Requires-Dist: mdanalysis
Requires-Dist: numpy<2.0,>=1.25
Requires-Dist: pandas
Requires-Dist: pdb-tools
Requires-Dist: requests
Requires-Dist: scikit-learn
Requires-Dist: seaborn
Requires-Dist: sequence-models
Requires-Dist: tqdm
Dynamic: classifier
Dynamic: description
Dynamic: description-content-type
Dynamic: home-page
Dynamic: license-file
Dynamic: requires-dist
Dynamic: requires-python
Dynamic: summary
